liste_iniziativa_medica/__init__.py
liste_iniziativa_medica/__main__.py
liste_iniziativa_medica/gui.py
liste_iniziativa_medica/helpers.py
liste_iniziativa_medica/list.py
liste_iniziativa_medica-0.2.5.dist-info/LICENSE
liste_iniziativa_medica-0.2.5.dist-info/METADATA
liste_iniziativa_medica-0.2.5.dist-info/WHEEL
liste_iniziativa_medica-0.2.5.dist-info/entry_points.txt
liste_iniziativa_medica-0.2.5.dist-info/top_level.txt
liste_iniziativa_medica-0.2.5.dist-info/RECORD
