Metadata-Version: 2.1
Name: liste-iniziativa-medica
Version: 0.2.5
Summary: Package per il generatore di liste di Iniziativa Medica
Author: Nicolò Nalin
Author-email: niconalin@gmail.com
License: MIT
Platform: UNKNOWN
Classifier: Programming Language :: Python :: 3
Classifier: License :: OSI Approved :: MIT License
Classifier: Operating System :: OS Independent
Requires-Python: >=3.6
License-File: LICENSE
